setup.py
prms_distributions/Binomialdistribution.py
prms_distributions/Gaussiandistribution.py
prms_distributions/Generaldistribution.py
prms_distributions/__init__.py
prms_distributions.egg-info/PKG-INFO
prms_distributions.egg-info/SOURCES.txt
prms_distributions.egg-info/dependency_links.txt
prms_distributions.egg-info/not-zip-safe
prms_distributions.egg-info/top_level.txt